electricitymaps_airflow_scheduler-0.1.0.dist-info/licenses/LICENSE
examples/__init__.py
examples/scheduled_workflow.py
src/electricitymaps_airflow_scheduler/__init__.py
src/electricitymaps_airflow_scheduler/scheduler.py
src/electricitymaps_airflow_scheduler/lib/__init__.py
src/electricitymaps_airflow_scheduler/lib/electricitymaps.py
electricitymaps_airflow_scheduler-0.1.0.dist-info/METADATA
electricitymaps_airflow_scheduler-0.1.0.dist-info/WHEEL
electricitymaps_airflow_scheduler-0.1.0.dist-info/entry_points.txt
electricitymaps_airflow_scheduler-0.1.0.dist-info/top_level.txt
electricitymaps_airflow_scheduler-0.1.0.dist-info/RECORD
